WorkingWithFiles/WorkingWithFiles.py
WorkingWithFiles/__init__.py
WorkingWithFiles/about.py
WorkingWithFiles/datasetfuncs.py
workingwithfiles-0.1.3.dist-info/licenses/LICENSE
workingwithfiles-0.1.3.dist-info/METADATA
workingwithfiles-0.1.3.dist-info/WHEEL
workingwithfiles-0.1.3.dist-info/top_level.txt
workingwithfiles-0.1.3.dist-info/RECORD
